AspnetMvc5GettingStarted/README.md
AspnetMvc5GettingStarted/__init__.py
AspnetMvc5GettingStarted/__main__.py
AspnetMvc5GettingStarted/file.epub
AspnetMvc5GettingStarted/index.html
AspnetMvc5GettingStarted/css/__init__.py
AspnetMvc5GettingStarted/css/annotations.css
AspnetMvc5GettingStarted/css/main.css
AspnetMvc5GettingStarted/css/normalize.css
AspnetMvc5GettingStarted/css/popup.css
AspnetMvc5GettingStarted/font/__init__.py
AspnetMvc5GettingStarted/font/fontello.eot
AspnetMvc5GettingStarted/font/fontello.svg
AspnetMvc5GettingStarted/font/fontello.ttf
AspnetMvc5GettingStarted/font/fontello.woff
AspnetMvc5GettingStarted/img/__init__.py
AspnetMvc5GettingStarted/img/annotator-glyph-sprite.png
AspnetMvc5GettingStarted/img/annotator-icon-sprite.png
AspnetMvc5GettingStarted/img/apple-touch-icon.png
AspnetMvc5GettingStarted/img/cancelfullscreen.png
AspnetMvc5GettingStarted/img/close.png
AspnetMvc5GettingStarted/img/fullscreen.png
AspnetMvc5GettingStarted/img/loader.gif
AspnetMvc5GettingStarted/img/menu-icon.png
AspnetMvc5GettingStarted/img/save.png
AspnetMvc5GettingStarted/img/saved.png
AspnetMvc5GettingStarted/img/settings-s.png
AspnetMvc5GettingStarted/img/settings.png
AspnetMvc5GettingStarted/img/star.png
AspnetMvc5GettingStarted/js/__init__.py
AspnetMvc5GettingStarted/js/epub.js
AspnetMvc5GettingStarted/js/epub.min.js
AspnetMvc5GettingStarted/js/epub.min.map
AspnetMvc5GettingStarted/js/hooks.min.js
AspnetMvc5GettingStarted/js/hooks.min.map
AspnetMvc5GettingStarted/js/reader.js
AspnetMvc5GettingStarted/js/reader.js.map
AspnetMvc5GettingStarted/js/reader.min.js
AspnetMvc5GettingStarted/js/reader.min.map
AspnetMvc5GettingStarted/js/hooks/__init__.py
AspnetMvc5GettingStarted/js/hooks/extensions/__init__.py
AspnetMvc5GettingStarted/js/hooks/extensions/highlight.js
AspnetMvc5GettingStarted/js/libs/__init__.py
AspnetMvc5GettingStarted/js/libs/jquery.min.js
AspnetMvc5GettingStarted/js/libs/localforage.min.js
AspnetMvc5GettingStarted/js/libs/screenfull.js
aspnet_mvc5_getting_started-2024.3.1.0.dist-info/METADATA
aspnet_mvc5_getting_started-2024.3.1.0.dist-info/WHEEL
aspnet_mvc5_getting_started-2024.3.1.0.dist-info/entry_points.txt
aspnet_mvc5_getting_started-2024.3.1.0.dist-info/top_level.txt
aspnet_mvc5_getting_started-2024.3.1.0.dist-info/RECORD
